{
"clients": [
    {
      "clientId": "demo1-app",
      "name": "demo1 Application",
      "enabled": true,
      "protocol": "openid-connect",

      "publicClient": false,
      "clientAuthenticatorType": "client-secret",
      "secret": "demo1-secret",

      "standardFlowEnabled": true,
      "directAccessGrantsEnabled": true,
      "serviceAccountsEnabled": true,

      "redirectUris": [ "http://c-demo-app1:8080/*" ],
      "webOrigins": [ "http://c-demo-app1:8080" ],

      "defaultClientScopes": [ "web-origins", "profile", "email", "roles" ],
      "optionalClientScopes": [ "address", "phone", "offline_access"
      ]
    }
  ]
}
